yors_comfyui_node_setup/__init__.py
yors_comfyui_node_setup/main.py
yors_comfyui_node_setup-0.11.0.dist-info/METADATA
yors_comfyui_node_setup-0.11.0.dist-info/WHEEL
yors_comfyui_node_setup-0.11.0.dist-info/RECORD
