Metadata-Version: 2.1
Name: yors_comfyui_node_setup
Version: 0.11.0
Summary: A python library for setup comfyui custom nodes for developers in development
Home-page: https://github.com/ymc-github/panz/blob/main/packages/yors_comfyui_node_setup/README.md
License: LICENSE
Keywords: artist,panz,mono,yors_comfyui_node_setup
Author: yemiancheng
Author-email: ymc.github@gmail.com
Requires-Python: >=3.10,<4.0
Classifier: Development Status :: 3 - Alpha
Classifier: Intended Audience :: Developers
Classifier: License :: OSI Approved :: MIT License
Classifier: License :: Other/Proprietary License
Classifier: Programming Language :: Python :: 3
Classifier: Programming Language :: Python :: 3.10
Classifier: Programming Language :: Python :: 3.11
Classifier: Programming Language :: Python :: 3.12
Classifier: Topic :: Software Development :: Build Tools
Project-URL: Documentation, https://github.com/ymc-github/panz/blob/main/packages/yors_comfyui_node_setup/README.md
Project-URL: Repository, https://github.com/ymc-github/panz.git
Project-URL: changelog, https://github.com/ymc-github/panz/blob/main/packages/yors_comfyui_node_setup/CHANGELOG.md
